autocomplete_widget
